xivgear_wrapper_Cedohran/__init__.py
xivgear_wrapper_Cedohran/example.py
xivgear_wrapper_Cedohran/xivapi/xiv_api.py
xivgear_wrapper_Cedohran/xivgear/xiv_gear_api.py
xivgear_wrapper_Cedohran/xivgear/xiv_gear_item.py
xivgear_wrapper_Cedohran/xivgear/xiv_gear_set.py
xivgear_wrapper_cedohran-0.0.3.dist-info/METADATA
xivgear_wrapper_cedohran-0.0.3.dist-info/WHEEL
xivgear_wrapper_cedohran-0.0.3.dist-info/licenses/LICENSE
xivgear_wrapper_cedohran-0.0.3.dist-info/RECORD
